ksuid_pydantic/__init__.py
ksuid_pydantic/ksuid.py
ksuid_pydantic-0.3.0.dist-info/WHEEL
ksuid_pydantic-0.3.0.dist-info/METADATA
ksuid_pydantic-0.3.0.dist-info/RECORD
